hack4u/__init__.py
hack4u/courses.py
LFCursos-0.1.0.dist-info/METADATA
LFCursos-0.1.0.dist-info/WHEEL
LFCursos-0.1.0.dist-info/top_level.txt
LFCursos-0.1.0.dist-info/RECORD
