Metadata-Version: 2.1
Name: LFCursos
Version: 0.1.0
Summary: Una biblioteca para consultar cursos de Hack4u.
Home-page: https://hack4u.io
Author: Carlos López
